diffusionlab/__init__.py
diffusionlab/dynamics.py
diffusionlab/losses.py
diffusionlab/samplers.py
diffusionlab/schedulers.py
diffusionlab/vector_fields.py
diffusionlab/distributions/__init__.py
diffusionlab/distributions/base.py
diffusionlab/distributions/empirical.py
diffusionlab/distributions/gmm/__init__.py
diffusionlab/distributions/gmm/gmm.py
diffusionlab/distributions/gmm/iso_gmm.py
diffusionlab/distributions/gmm/iso_hom_gmm.py
diffusionlab/distributions/gmm/low_rank_gmm.py
diffusionlab/distributions/gmm/utils.py
diffusionlab-3.0.4.dist-info/METADATA
diffusionlab-3.0.4.dist-info/WHEEL
diffusionlab-3.0.4.dist-info/licenses/LICENSE
diffusionlab-3.0.4.dist-info/RECORD
