Metadata-Version: 2.4
Name: diffusionlab
Version: 3.0.4
Summary: Easy no-frills implementations of common abstractions for diffusion models.
License-File: LICENSE
Requires-Python: >=3.12
Requires-Dist: jax>=0.6.0
Provides-Extra: dev
Requires-Dist: matplotlib>=3.10.1; extra == 'dev'
Requires-Dist: pytest-cov>=6.0.0; extra == 'dev'
Requires-Dist: pytest>=8.3.5; extra == 'dev'
Requires-Dist: ruff>=0.11.0; extra == 'dev'
Provides-Extra: docs
Requires-Dist: furo>=2024.8.6; extra == 'docs'
Requires-Dist: myst-parser>=4.0.1; extra == 'docs'
Requires-Dist: sphinx>=8.2.3; extra == 'docs'
